sksparse/cholmod.cpython-311-darwin.so
graphite_maps/version.py
graphite_maps/enif.py
graphite_maps/__init__.py
graphite_maps/precision_estimation.py
graphite_maps/linear_regression.py
graphite_maps/sksparse/__init__.py
graphite_maps/sksparse/cholmod.pyx
graphite_maps/sksparse/test_cholmod.py
graphite_maps/.dylibs/libcholmod.5.3.4.dylib
graphite_maps/.dylibs/libccolamd.3.3.5.dylib
graphite_maps/.dylibs/libcamd.3.3.5.dylib
graphite_maps/.dylibs/libgfortran.5.dylib
graphite_maps/.dylibs/libsuitesparseconfig.7.12.1.dylib
graphite_maps/.dylibs/libcolamd.3.3.5.dylib
graphite_maps/.dylibs/libquadmath.0.dylib
graphite_maps/.dylibs/libgcc_s.1.1.dylib
graphite_maps/.dylibs/libgomp.1.dylib
graphite_maps/.dylibs/libamd.3.3.4.dylib
graphite_maps-0.0.4.dist-info/RECORD
graphite_maps-0.0.4.dist-info/WHEEL
graphite_maps-0.0.4.dist-info/top_level.txt
graphite_maps-0.0.4.dist-info/METADATA
graphite_maps-0.0.4.dist-info/licenses/LICENSE_libsuitesparse_cholmod.txt
graphite_maps-0.0.4.dist-info/licenses/LICENSE
graphite_maps-0.0.4.dist-info/licenses/LICENSE_libsuitesparse.txt
