Metadata-Version: 2.4
Name: graphite-maps
Version: 0.0.4
Summary: Ensemble based data assimilation learning graph informed triangular ensemble-to-posterior transport maps from data
Author: Berent Lunde
Requires-Python: <3.15,>=3.10
License-File: LICENSE
License-File: LICENSE_libsuitesparse_cholmod.txt
License-File: LICENSE_libsuitesparse.txt
Requires-Dist: matplotlib
Requires-Dist: scipy
Requires-Dist: scikit-learn
Requires-Dist: networkx
Requires-Dist: tqdm
Provides-Extra: dev
Requires-Dist: pre-commit; extra == "dev"
Requires-Dist: pytest; extra == "dev"
Requires-Dist: scikit-sparse; extra == "dev"
Dynamic: license-file
